<?xml version="1.0" encoding="UTF-8"?>
<objects serializationModel="Studio.02.00.00">
	<object class="AudioFile" id="{30ff0a13-0fec-4531-8540-2788016772dd}">
		<property name="assetPath">
			<value>peasant-neutral-2.wav</value>
		</property>
		<property name="frequencyInKHz">
			<value>44.0999985</value>
		</property>
		<property name="channelCount">
			<value>2</value>
		</property>
		<property name="length">
			<value>0.87172335600907025</value>
		</property>
		<relationship name="masterAssetFolder">
			<destination>{b2cfb548-48f0-4bb6-b9d9-7a5157642177}</destination>
		</relationship>
	</object>
</objects>
